aoirint_miyadaiku_theme_blog/__init__.py
aoirint_miyadaiku_theme_blog/config.yml
aoirint_miyadaiku_theme_blog/contents/atom.yml
aoirint_miyadaiku_theme_blog/contents/index.yml
aoirint_miyadaiku_theme_blog/contents/index_category.yml
aoirint_miyadaiku_theme_blog/contents/index_tag.yml
aoirint_miyadaiku_theme_blog/contents/rss.yml
aoirint_miyadaiku_theme_blog/files/static/aoirint-blog/css/style.css
aoirint_miyadaiku_theme_blog/files/static/aoirint-blog/js/main.js
aoirint_miyadaiku_theme_blog/templates/base.html
aoirint_miyadaiku_theme_blog/templates/page_article.html
aoirint_miyadaiku_theme_blog/templates/page_group.html
aoirint_miyadaiku_theme_blog/templates/page_index.html
aoirint_miyadaiku_theme_blog/templates/part_category.html
aoirint_miyadaiku_theme_blog-0.1.15.dist-info/LICENSE
aoirint_miyadaiku_theme_blog-0.1.15.dist-info/METADATA
aoirint_miyadaiku_theme_blog-0.1.15.dist-info/WHEEL
aoirint_miyadaiku_theme_blog-0.1.15.dist-info/top_level.txt
aoirint_miyadaiku_theme_blog-0.1.15.dist-info/RECORD
